Tulib/Tulib.py
Tulib/__init__.py
Tulib-0.1.0.dist-info/METADATA
Tulib-0.1.0.dist-info/WHEEL
Tulib-0.1.0.dist-info/top_level.txt
Tulib-0.1.0.dist-info/RECORD
